yaltai/__init__.py
yaltai/converter.py
yaltai/kraken_adapter.py
yaltai/kraken_yaltai.py
yaltai/preprocessing.py
yaltai/template.xml
yaltai/utils.py
yaltai/yaltai.py
yaltai/yolo_adapter.py
yaltai/cli/__init__.py
yaltai/cli/krakn.py
yaltai/cli/yaltai.py
yaltai/models/__init__.py
yaltai/models/krakn.py
yaltai/models/yolo.py
YALTAi-2.0.5.dist-info/LICENSE
YALTAi-2.0.5.dist-info/METADATA
YALTAi-2.0.5.dist-info/WHEEL
YALTAi-2.0.5.dist-info/entry_points.txt
YALTAi-2.0.5.dist-info/top_level.txt
YALTAi-2.0.5.dist-info/RECORD
