Metadata-Version: 2.1
Name: YALTAi
Version: 2.0.5
Summary: You Actually Look Twice At it, YOLOv5-Kraken adapter for region detection 
Home-page: https://github.com/ponteineptique/yaltai
Author: Thibault Clérice
License: MIT
Platform: UNKNOWN
Classifier: License :: OSI Approved :: MIT License
Classifier: Programming Language :: Python
Classifier: Programming Language :: Python :: 3
Classifier: Programming Language :: Python :: 3.8
Classifier: Programming Language :: Python :: Implementation :: CPython
Classifier: Programming Language :: Python :: Implementation :: PyPy
Classifier: Topic :: Text Processing :: Linguistic
Requires-Python: >=3.8.0
License-File: LICENSE
Requires-Dist: fast-deskew (==1.0)
Requires-Dist: kraken (~=5.3.0)
Requires-Dist: mean-average-precision (==2021.4.26.0)
Requires-Dist: tabulate (~=0.8.10)
Requires-Dist: ultralytics (~=8.3.0)
